<?xml version="1.0" encoding="UTF-8"?>
<precedent xmlns="http://law.2nx.info/xml_precedent">
  <基本情報>
    <下級裁判例>
      <事件番号>平成15(わ)6</事件番号>
      <事件名>殺人，窃盗被告事件</事件名>
      <裁判年月日>平成15年06月19日</裁判年月日>
      <裁判所名・部>函館地方裁判所</裁判所名・部>
      <PDFs>
        <PDF type="全文">http://www.courts.go.jp/hanrei/pdf/57F3B7CCF1F16C4049256D550022E049.pdf</PDF>
        <PDF type="別紙１">http://www.courts.go.jp/tenpu/pdf4/57F3B7CCF1F16C4049256D550022E049-1.pdf</PDF>
      </PDFs>
      <URL>http://www.courts.go.jp/search/jhsp0030?hanreiid=8711&amp;hanreiKbn=04</URL>
    </下級裁判例>
  </基本情報>
  <判決文>
    <裁判官>
    </裁判官>
  </判決文>
</precedent>
