<?xml version="1.0" encoding="UTF-8"?>
<precedent xmlns="http://law.2nx.info/xml_precedent">
  <基本情報>
    <最高裁判例>
      <事件番号>平成21(受)1192</事件番号>
      <事件名>不当利得返還請求事件</事件名>
      <裁判年月日>平成21年09月04日</裁判年月日>
      <法廷名>最高裁判所第二小法廷</法廷名>
      <裁判種別>判決</裁判種別>
      <結果>棄却</結果>
      <判例集等巻・号・頁>集民　第231号477頁</判例集等巻・号・頁>
      <原審裁判所名>東京高等裁判所</原審裁判所名>
      <原審事件番号>平成21(ネ)60</原審事件番号>
      <原審裁判年月日>平成21年03月26日</原審裁判年月日>
      <判示事項>
        <項目>いわゆる過払金充当合意を含む基本契約に基づく金銭消費貸借の借主が利息制限法所定の制限を超える利息の支払を継続したことにより過払金が発生した場合における，民法７０４条前段所定の利息の発生時期<br /><br /></項目>
      </判示事項>
      <裁判要旨>
        <項目>いわゆる過払金充当合意（過払金発生当時他の借入金債務が存在しなければ過払金をその後に発生する新たな借入金債務に充当する旨の合意）を含む基本契約に基づく金銭消費貸借の借主が利息制限法所定の制限を超える利息の支払を継続したことにより過払金が発生した場合においても，悪意の受益者である貸主は過払金発生の時から民法７０４条前段所定の利息を支払わなければならない。<br /></項目>
      </裁判要旨>
      <参照法条>
        <項目>民法704条前段</項目>
        <項目>利息制限法1条1項</項目>
      </参照法条>
      <PDFs>
        <PDF type="全文">http://www.courts.go.jp/hanrei/pdf/20090904111138.pdf</PDF>
      </PDFs>
      <URL>http://www.courts.go.jp/search/jhsp0030?hanreiid=37953&amp;hanreiKbn=02</URL>
    </最高裁判例>
  </基本情報>
  <判決文>
    <主文前>
      主文本件上告を棄却する。
      上告費用は上告人の負担とする。
      理由上告代理人前田陽司，同黒澤幸恵，同菊川秀明の上告受理申立て理由について１金銭消費貸借の借主が利息制限法１条１項所定の制限を超えて利息の支払を継続し，その制限超過部分を元本に充当すると過払金が発生した場合において，貸主が悪意の受益者であるときは，貸主は，民法７０４条前段の規定に基づき，過払金発生の時から同条前段所定の利息を支払わなければならない（大審院昭和２年（オ）第１９５号同年１２月２６日判決・法律新聞２８０６号１５頁参照）。
      このことは，金銭消費貸借が，貸主と借主との間で継続的に金銭の借入れとその弁済が繰り返される旨の基本契約に基づくものであって，当該基本契約が過払金が発生した当時他の借入金債務が存在しなければ過払金をその後に発生する新たな借入金債務に充当する旨の合意を含むものであった場合でも，異なるところはないと解するのが相当である。
      ２以上と同旨の原審の判断は，正当として是認することができる。
      論旨は採用することができない。
      よって，裁判官全員一致の意見で，主文のとおり判決する。
    (裁判長裁判官古田佑紀</主文前>
    <裁判官>
    </裁判官>
  </判決文>
</precedent>
